[
  {
    "uraian": "GA Program Infrastruktur Konektivitas",
    "kode_akun": null,
    "level": "program",
    "pagu": 10814731000,
    "realisasi_lalu": 3350859563,
    "realisasi_ini": 692787926,
    "realisasi_sd": 4043647489,
    "persen": 37.39,
    "sisa": 6771083511
  },
  {
    "uraian": "GA.7696 Pembangunan dan Preservasi Jalan Nasional",
    "kode_akun": null,
    "level": "program",
    "pagu": 10814731000,
    "realisasi_lalu": 3350859563,
    "realisasi_ini": 692787926,
    "realisasi_sd": 4043647489,
    "persen": 37.39,
    "sisa": 6771083511
  },
  {
    "uraian": "CBR Dukungan Teknis",
    "kode_akun": null,
    "level": "kegiatan",
    "pagu": 10814731000,
    "realisasi_lalu": 3350859563,
    "realisasi_ini": 692787926,
    "realisasi_sd": 4043647489,
    "persen": 37.39,
    "sisa": 6771083511
  },
  {
    "uraian": "CBR.001 Layanan Penyiapan dan Pengendalian Pelaksanaan",
    "kode_akun": null,
    "level": "kegiatan",
    "pagu": 441855000,
    "realisasi_lalu": 212628180,
    "realisasi_ini": 15537087,
    "realisasi_sd": 228165267,
    "persen": 51.64,
    "sisa": 213689733
  },
  {
    "uraian": "401.0 Monitoring Dan Evaluasi",
    "kode_akun": null,
    "level": "item",
    "pagu": 243855000,
    "realisasi_lalu": 62628180,
    "realisasi_ini": 15537087,
    "realisasi_sd": 78165267,
    "persen": 32.05,
    "sisa": 165689733
  },
  {
    "uraian": "401.AA Monitoring dan Evaluasi Pelaksanaan Paket-Paket Jalan Nasional Satker",
    "kode_akun": null,
    "level": "komponen",
    "pagu": 109406000,
    "realisasi_lalu": 18428080,
    "realisasi_ini": 0,
    "realisasi_sd": 18428080,
    "persen": 16.84,
    "sisa": 90977920
  },
  {
    "uraian": "521211.0 Belanja Bahan",
    "kode_akun": "521211",
    "level": "akun",
    "pagu": 1700000,
    "realisasi_lalu": 0,
    "realisasi_ini": 0,
    "realisasi_sd": 0,
    "persen": 0.0,
    "sisa": 1700000
  },
  {
    "uraian": "000010. Biaya Penggandaan laporan",
    "kode_akun": null,
    "level": "item",
    "pagu": 1200000,
    "realisasi_lalu": 0,
    "realisasi_ini": 0,
    "realisasi_sd": 0,
    "persen": 0.0,
    "sisa": 1200000
  },
  {
    "uraian": "000011. Alat Tulis Kantor",
    "kode_akun": null,
    "level": "item",
    "pagu": 500000,
    "realisasi_lalu": 0,
    "realisasi_ini": 0,
    "realisasi_sd": 0,
    "persen": 0.0,
    "sisa": 500000
  },
  {
    "uraian": "522141.0 Belanja Sewa",
    "kode_akun": "522141",
    "level": "akun",
    "pagu": 38998000,
    "realisasi_lalu": 6290000,
    "realisasi_ini": 0,
    "realisasi_sd": 6290000,
    "persen": 16.13,
    "sisa": 32708000
  },
  {
    "uraian": "000175. Sewa Kendaraan Roda 4 (Bangka  Belitung)",
    "kode_akun": null,
    "level": "item",
    "pagu": 11322000,
    "realisasi_lalu": 1258000,
    "realisasi_ini": 0,
    "realisasi_sd": 1258000,
    "persen": 11.11,
    "sisa": 10064000
  },
  {
    "uraian": "000177. Sewa Kendaraan Roda 4 (Bangka  Belitung)",
    "kode_akun": null,
    "level": "item",
    "pagu": 11322000,
    "realisasi_lalu": 1258000,
    "realisasi_ini": 0,
    "realisasi_sd": 1258000,
    "persen": 11.11,
    "sisa": 10064000
  },
  {
    "uraian": "000179. Sewa Kendaraan Roda 4 (Bangka  Belitung)",
    "kode_akun": null,
    "level": "item",
    "pagu": 11322000,
    "realisasi_lalu": 1258000,
    "realisasi_ini": 0,
    "realisasi_sd": 1258000,
    "persen": 11.11,
    "sisa": 10064000
  },
  {
    "uraian": "000181. Sewa Kendaraan Roda 4 (Bangka  Belitung)",
    "kode_akun": null,
    "level": "item",
    "pagu": 5032000,
    "realisasi_lalu": 2516000,
    "realisasi_ini": 0,
    "realisasi_sd": 2516000,
    "persen": 50.0,
    "sisa": 2516000
  },
  {
    "uraian": "524111.0 Belanja Perjalanan Dinas Biasa",
    "kode_akun": "524111",
    "level": "akun",
    "pagu": 68708000,
    "realisasi_lalu": 12138080,
    "realisasi_ini": 0,
    "realisasi_sd": 12138080,
    "persen": 17.67,
    "sisa": 56569920
  },
  {
    "uraian": "000015. Uang Harian Perjalanan Dinas Luar Kota (Bangka  Belitung)",
    "kode_akun": null,
    "level": "item",
    "pagu": 40590000,
    "realisasi_lalu": 1230000,
    "realisasi_ini": 0,
    "realisasi_sd": 1230000,
    "persen": 3.03,
    "sisa": 39360000
  },
  {
    "uraian": "000017. Biaya Tiket Pesawat Pangkalpinang (Bangka) - Tj. Pandan (Belitung)",
    "kode_akun": null,
    "level": "item",
    "pagu": 10500000,
    "realisasi_lalu": 4080080,
    "realisasi_ini": 0,
    "realisasi_sd": 4080080,
    "persen": 38.86,
    "sisa": 6419920
  },
  {
    "uraian": "000018. Biaya Penginapan Perjalanan Dinas Pejabat  Eselon IV/Golongan III  (BANGKA  BELITUNG)",
    "kode_akun": null,
    "level": "item",
    "pagu": 10136000,
    "realisasi_lalu": 4344000,
    "realisasi_ini": 0,
    "realisasi_sd": 4344000,
    "persen": 42.86,
    "sisa": 5792000
  },
  {
    "uraian": "000019. Uang Harian Perjalanan Dinas Luar Kota (Bangka  Belitung)",
    "kode_akun": null,
    "level": "item",
    "pagu": 6970000,
    "realisasi_lalu": 2214000,
    "realisasi_ini": 0,
    "realisasi_sd": 2214000,
    "persen": 31.76,
    "sisa": 4756000
  },
  {
    "uraian": "000020. Biaya Transportasi dari dan/atau ke Terminal Bus/Stasiun/Bandara/Pelabuhan Dalam Rangka Perjalanan Dinas Dalam Negeri (Bangka Beli",
    "kode_akun": null,
    "level": "item",
    "pagu": 512000,
    "realisasi_lalu": 270000,
    "realisasi_ini": 0,
    "realisasi_sd": 270000,
    "persen": 52.73,
    "sisa": 242000
  },
  {
    "uraian": "401.AB Monitoring dan Evaluasi Pelaksanaan Paket-Paket Jalan Nasional PPK Perencanaan",
    "kode_akun": null,
    "level": "komponen",
    "pagu": 29173000,
    "realisasi_lalu": 4320000,
    "realisasi_ini": 4284100,
    "realisasi_sd": 8604100,
    "persen": 29.49,
    "sisa": 20568900
  },
  {
    "uraian": "521211.0 Belanja Bahan",
    "kode_akun": "521211",
    "level": "akun",
    "pagu": 2486000,
    "realisasi_lalu": 0,
    "realisasi_ini": 0,
    "realisasi_sd": 0,
    "persen": 0.0,
    "sisa": 2486000
  },
  {
    "uraian": "000030. Biaya Penggandaan laporan",
    "kode_akun": null,
    "level": "item",
    "pagu": 1243000,
    "realisasi_lalu": 0,
    "realisasi_ini": 0,
    "realisasi_sd": 0,
    "persen": 0.0,
    "sisa": 1243000
  },
  {
    "uraian": "000031. Alat Tulis Kantor",
    "kode_akun": null,
    "level": "item",
    "pagu": 1243000,
    "realisasi_lalu": 0,
    "realisasi_ini": 0,
    "realisasi_sd": 0,
    "persen": 0.0,
    "sisa": 1243000
  },
  {
    "uraian": "522141.0 Belanja Sewa",
    "kode_akun": "522141",
    "level": "akun",
    "pagu": 18870000,
    "realisasi_lalu": 2516000,
    "realisasi_ini": 0,
    "realisasi_sd": 2516000,
    "persen": 13.33,
    "sisa": 16354000
  },
  {
    "uraian": "000184. Sewa Kendaraan Roda 4 (Bangka  Belitung)",
    "kode_akun": null,
    "level": "item",
    "pagu": 18870000,
    "realisasi_lalu": 2516000,
    "realisasi_ini": 0,
    "realisasi_sd": 2516000,
    "persen": 13.33,
    "sisa": 16354000
  },
  {
    "uraian": "524111.0 Belanja Perjalanan Dinas Biasa",
    "kode_akun": "524111",
    "level": "akun",
    "pagu": 7817000,
    "realisasi_lalu": 1804000,
    "realisasi_ini": 4284100,
    "realisasi_sd": 6088100,
    "persen": 77.88,
    "sisa": 1728900
  },
  {
    "uraian": "000033. Biaya Tiket Pesawat Pangkalpinang (Bangka) - Tj. Pandan (Belitung)",
    "kode_akun": null,
    "level": "item",
    "pagu": 1300000,
    "realisasi_lalu": 0,
    "realisasi_ini": 1300000,
    "realisasi_sd": 1300000,
    "persen": 100.0,
    "sisa": 0
  },
  {
    "uraian": "000034. Biaya Penginapan Perjalanan Dinas Pejabat  Eselon IV/Golongan III  (BANGKA  BELITUNG)",
    "kode_akun": null,
    "level": "item",
    "pagu": 1400000,
    "realisasi_lalu": 0,
    "realisasi_ini": 1400000,
    "realisasi_sd": 1400000,
    "persen": 100.0,
    "sisa": 0
  },
  {
    "uraian": "000035. Uang Harian Perjalanan Dinas Luar Kota (Bangka  Belitung)",
    "kode_akun": null,
    "level": "item",
    "pagu": 1339000,
    "realisasi_lalu": 0,
    "realisasi_ini": 1338100,
    "realisasi_sd": 1338100,
    "persen": 99.93,
    "sisa": 900
  },
  {
    "uraian": "000043. Uang Harian Perjalanan Dinas Luar Kota (Bangka  Belitung)",
    "kode_akun": null,
    "level": "item",
    "pagu": 3778000,
    "realisasi_lalu": 1804000,
    "realisasi_ini": 246000,
    "realisasi_sd": 2050000,
    "persen": 54.26,
    "sisa": 1728000
  },
  {
    "uraian": "401.AC Monitoring dan Evaluasi Pelaksanaan Paket-Paket Jalan Nasional PPK Pengawasan",
    "kode_akun": null,
    "level": "komponen",
    "pagu": 28426000,
    "realisasi_lalu": 24053010,
    "realisasi_ini": 0,
    "realisasi_sd": 24053010,
    "persen": 84.62,
    "sisa": 4372990
  },
  {
    "uraian": "521211.0 Belanja Bahan",
    "kode_akun": "521211",
    "level": "akun",
    "pagu": 1275000,
    "realisasi_lalu": 0,
    "realisasi_ini": 0,
    "realisasi_sd": 0,
    "persen": 0.0,
    "sisa": 1275000
  },
  {
    "uraian": "000047. Alat Tulis Kantor",
    "kode_akun": null,
    "level": "item",
    "pagu": 1275000,
    "realisasi_lalu": 0,
    "realisasi_ini": 0,
    "realisasi_sd": 0,
    "persen": 0.0,
    "sisa": 1275000
  },
  {
    "uraian": "522141.0 Belanja Sewa",
    "kode_akun": "522141",
    "level": "akun",
    "pagu": 11322000,
    "realisasi_lalu": 8806000,
    "realisasi_ini": 0,
    "realisasi_sd": 8806000,
    "persen": 77.78,
    "sisa": 2516000
  },
  {
    "uraian": "000189. Sewa Kendaraan Roda 4 (Bangka  Belitung)",
    "kode_akun": null,
    "level": "item",
    "pagu": 6290000,
    "realisasi_lalu": 3774000,
    "realisasi_ini": 0,
    "realisasi_sd": 3774000,
    "persen": 60.0,
    "sisa": 2516000
  },
  {
    "uraian": "000191. Sewa Kendaraan Roda 4 (Bangka  Belitung)",
    "kode_akun": null,
    "level": "item",
    "pagu": 5032000,
    "realisasi_lalu": 5032000,
    "realisasi_ini": 0,
    "realisasi_sd": 5032000,
    "persen": 100.0,
    "sisa": 0
  },
  {
    "uraian": "524111.0 Belanja Perjalanan Dinas Biasa",
    "kode_akun": "524111",
    "level": "akun",
    "pagu": 15829000,
    "realisasi_lalu": 15247010,
    "realisasi_ini": 0,
    "realisasi_sd": 15247010,
    "persen": 96.32,
    "sisa": 581990
  },
  {
    "uraian": "000049. Biaya Tiket Pesawat Pangkalpinang (Bangka) - Tj. Pandan (Belitung)",
    "kode_akun": null,
    "level": "item",
    "pagu": 5035000,
    "realisasi_lalu": 5034230,
    "realisasi_ini": 0,
    "realisasi_sd": 5034230,
    "persen": 99.98,
    "sisa": 770
  },
  {
    "uraian": "000050. Biaya Penginapan Perjalanan Dinas Pejabat  Eselon IV/Golongan III  (BANGKA  BELITUNG)",
    "kode_akun": null,
    "level": "item",
    "pagu": 5792000,
    "realisasi_lalu": 5792000,
    "realisasi_ini": 0,
    "realisasi_sd": 5792000,
    "persen": 100.0,
    "sisa": 0
  },
  {
    "uraian": "000051. Uang Harian Perjalanan Dinas Luar Kota (Bangka  Belitung)",
    "kode_akun": null,
    "level": "item",
    "pagu": 2952000,
    "realisasi_lalu": 2952000,
    "realisasi_ini": 0,
    "realisasi_sd": 2952000,
    "persen": 100.0,
    "sisa": 0
  },
  {
    "uraian": "000052. Biaya Transportasi dari dan/atau ke Terminal Bus/Stasiun/Bandara/Pelabuhan Dalam Rangka Perjalanan Dinas Dalam Negeri (Bangka Beli",
    "kode_akun": null,
    "level": "item",
    "pagu": 239000,
    "realisasi_lalu": 238780,
    "realisasi_ini": 0,
    "realisasi_sd": 238780,
    "persen": 99.91,
    "sisa": 220
  },
  {
    "uraian": "000059. Uang Harian Perjalanan Dinas Luar Kota (Bangka  Belitung)",
    "kode_akun": null,
    "level": "item",
    "pagu": 1811000,
    "realisasi_lalu": 1230000,
    "realisasi_ini": 0,
    "realisasi_sd": 1230000,
    "persen": 67.92,
    "sisa": 581000
  },
  {
    "uraian": "401.AD Sinkronisasi dan Koordinasi",
    "kode_akun": null,
    "level": "komponen",
    "pagu": 76850000,
    "realisasi_lalu": 15827090,
    "realisasi_ini": 11252987,
    "realisasi_sd": 27080077,
    "persen": 35.24,
    "sisa": 49769923
  },
  {
    "uraian": "524111.0 Belanja Perjalanan Dinas Biasa",
    "kode_akun": "524111",
    "level": "akun",
    "pagu": 76850000,
    "realisasi_lalu": 15827090,
    "realisasi_ini": 11252987,
    "realisasi_sd": 27080077,
    "persen": 35.24,
    "sisa": 49769923
  },
  {
    "uraian": "000062. Biaya Penginapan Perjalanan Dinas Pejabat  Eselon IV/Golongan III  (BANGKA  BELITUNG)",
    "kode_akun": null,
    "level": "item",
    "pagu": 7240000,
    "realisasi_lalu": 1448000,
    "realisasi_ini": 0,
    "realisasi_sd": 1448000,
    "persen": 20.0,
    "sisa": 5792000
  },
  {
    "uraian": "000063. Uang Harian Perjalanan Dinas Luar Kota (Bangka  Belitung)",
    "kode_akun": null,
    "level": "item",
    "pagu": 6150000,
    "realisasi_lalu": 2460000,
    "realisasi_ini": 0,
    "realisasi_sd": 2460000,
    "persen": 40.0,
    "sisa": 3690000
  },
  {
    "uraian": "000064. Biaya Transportasi dari dan/atau ke Terminal Bus/Stasiun/Bandara/Pelabuhan Dalam Rangka Perjalanan Dinas Dalam Negeri (Bangka Beli",
    "kode_akun": null,
    "level": "item",
    "pagu": 1000000,
    "realisasi_lalu": 517960,
    "realisasi_ini": 0,
    "realisasi_sd": 517960,
    "persen": 51.8,
    "sisa": 482040
  },
  {
    "uraian": "000066. Satuan Biaya Tiket Pesawat  Perjalanan Dinas Dalam Negeri (PP) Ekonomi JAKARTA - PANGKAL PINANG",
    "kode_akun": null,
    "level": "item",
    "pagu": 17112000,
    "realisasi_lalu": 1953336,
    "realisasi_ini": 6452987,
    "realisasi_sd": 8406323,
    "persen": 49.13,
    "sisa": 8705677
  },
  {
    "uraian": "000067. Biaya Penginapan Perjalanan Dinas Pejabat  Eselon IV/Golongan III  (D.K.I.  JAKARTA)",
    "kode_akun": null,
    "level": "item",
    "pagu": 17520000,
    "realisasi_lalu": 2881824,
    "realisasi_ini": 2220000,
    "realisasi_sd": 5101824,
    "persen": 29.12,
    "sisa": 12418176
  },
  {
    "uraian": "000068. Uang Harian Perjalanan Dinas Luar Kota (D.K.I.  Jakarta)",
    "kode_akun": null,
    "level": "item",
    "pagu": 16960000,
    "realisasi_lalu": 3246000,
    "realisasi_ini": 2580000,
    "realisasi_sd": 5826000,
    "persen": 34.35,
    "sisa": 11134000
  },
  {
    "uraian": "000069. Biaya Transportasi dari dan/atau ke Terminal Bus/Stasiun/Bandara/Pelabuhan Dalam Rangka Perjalanan Dinas Dalam Negeri (Bangka Beli",
    "kode_akun": null,
    "level": "item",
    "pagu": 2192000,
    "realisasi_lalu": 180000,
    "realisasi_ini": 0,
    "realisasi_sd": 180000,
    "persen": 8.21,
    "sisa": 2012000
  },
  {
    "uraian": "000070. Biaya Transportasi dari dan/atau ke Terminal Bus/Stasiun/Bandara/Pelabuhan Dalam Rangka Perjalanan Dinas Dalam Negeri (DKI Jakarta",
    "kode_akun": null,
    "level": "item",
    "pagu": 1176000,
    "realisasi_lalu": 436250,
    "realisasi_ini": 0,
    "realisasi_sd": 436250,
    "persen": 37.1,
    "sisa": 739750
  },
  {
    "uraian": "000072. Biaya Tiket Pesawat Pangkalpinang (Bangka) - Tj. Pandan (Belitung)",
    "kode_akun": null,
    "level": "item",
    "pagu": 7500000,
    "realisasi_lalu": 2703720,
    "realisasi_ini": 0,
    "realisasi_sd": 2703720,
    "persen": 36.05,
    "sisa": 4796280
  },
  {
    "uraian": "402.0 Manajemen Pengendalian",
    "kode_akun": null,
    "level": "item",
    "pagu": 198000000,
    "realisasi_lalu": 150000000,
    "realisasi_ini": 0,
    "realisasi_sd": 150000000,
    "persen": 75.76,
    "sisa": 48000000
  },
  {
    "uraian": "402.AE Manajemen Pengendalian Satker",
    "kode_akun": null,
    "level": "komponen",
    "pagu": 198000000,
    "realisasi_lalu": 150000000,
    "realisasi_ini": 0,
    "realisasi_sd": 150000000,
    "persen": 75.76,
    "sisa": 48000000
  },
  {
    "uraian": "521211.0 Belanja Bahan",
    "kode_akun": "521211",
    "level": "akun",
    "pagu": 48000000,
    "realisasi_lalu": 0,
    "realisasi_ini": 0,
    "realisasi_sd": 0,
    "persen": 0.0,
    "sisa": 48000000
  },
  {
    "uraian": "000213. Sepatu Safty",
    "kode_akun": null,
    "level": "item",
    "pagu": 4550000,
    "realisasi_lalu": 0,
    "realisasi_ini": 0,
    "realisasi_sd": 0,
    "persen": 0.0,
    "sisa": 4550000
  },
  {
    "uraian": "000214. Box Container Plastik Ukuran 280L",
    "kode_akun": null,
    "level": "item",
    "pagu": 7200000,
    "realisasi_lalu": 0,
    "realisasi_ini": 0,
    "realisasi_sd": 0,
    "persen": 0.0,
    "sisa": 7200000
  },
  {
    "uraian": "000215. Box Container Plastik Ukuran 150L",
    "kode_akun": null,
    "level": "item",
    "pagu": 2500000,
    "realisasi_lalu": 0,
    "realisasi_ini": 0,
    "realisasi_sd": 0,
    "persen": 0.0,
    "sisa": 2500000
  },
  {
    "uraian": "000216. Rompi Lapangan",
    "kode_akun": null,
    "level": "item",
    "pagu": 2450000,
    "realisasi_lalu": 0,
    "realisasi_ini": 0,
    "realisasi_sd": 0,
    "persen": 0.0,
    "sisa": 2450000
  },
  {
    "uraian": "000217. Meteran Dorong",
    "kode_akun": null,
    "level": "item",
    "pagu": 1150000,
    "realisasi_lalu": 0,
    "realisasi_ini": 0,
    "realisasi_sd": 0,
    "persen": 0.0,
    "sisa": 1150000
  },
  {
    "uraian": "000218. Meteran Laser",
    "kode_akun": null,
    "level": "item",
    "pagu": 1400000,
    "realisasi_lalu": 0,
    "realisasi_ini": 0,
    "realisasi_sd": 0,
    "persen": 0.0,
    "sisa": 1400000
  },
  {
    "uraian": "000219. Sigmat Digital",
    "kode_akun": null,
    "level": "item",
    "pagu": 475000,
    "realisasi_lalu": 0,
    "realisasi_ini": 0,
    "realisasi_sd": 0,
    "persen": 0.0,
    "sisa": 475000
  },
  {
    "uraian": "000220. Kipas Angin Pendingin",
    "kode_akun": null,
    "level": "item",
    "pagu": 2800000,
    "realisasi_lalu": 0,
    "realisasi_ini": 0,
    "realisasi_sd": 0,
    "persen": 0.0,
    "sisa": 2800000
  },
  {
    "uraian": "000221. Topi",
    "kode_akun": null,
    "level": "item",
    "pagu": 700000,
    "realisasi_lalu": 0,
    "realisasi_ini": 0,
    "realisasi_sd": 0,
    "persen": 0.0,
    "sisa": 700000
  },
  {
    "uraian": "000222. Tangga Teleskopik Alumunium",
    "kode_akun": null,
    "level": "item",
    "pagu": 775000,
    "realisasi_lalu": 0,
    "realisasi_ini": 0,
    "realisasi_sd": 0,
    "persen": 0.0,
    "sisa": 775000
  },
  {
    "uraian": "000234. Thermometer Pocket (Untuk Aspal)",
    "kode_akun": null,
    "level": "item",
    "pagu": 2400000,
    "realisasi_lalu": 0,
    "realisasi_ini": 0,
    "realisasi_sd": 0,
    "persen": 0.0,
    "sisa": 2400000
  },
  {
    "uraian": "000235. Thermometer Digital (Untuk Aspal)",
    "kode_akun": null,
    "level": "item",
    "pagu": 560000,
    "realisasi_lalu": 0,
    "realisasi_ini": 0,
    "realisasi_sd": 0,
    "persen": 0.0,
    "sisa": 560000
  },
  {
    "uraian": "000236. Sepatu Safty",
    "kode_akun": null,
    "level": "item",
    "pagu": 5840000,
    "realisasi_lalu": 0,
    "realisasi_ini": 0,
    "realisasi_sd": 0,
    "persen": 0.0,
    "sisa": 5840000
  },
  {
    "uraian": "000237. Helm Proyek",
    "kode_akun": null,
    "level": "item",
    "pagu": 2240000,
    "realisasi_lalu": 0,
    "realisasi_ini": 0,
    "realisasi_sd": 0,
    "persen": 0.0,
    "sisa": 2240000
  },
  {
    "uraian": "000238. Rompi Lapangan",
    "kode_akun": null,
    "level": "item",
    "pagu": 2720000,
    "realisasi_lalu": 0,
    "realisasi_ini": 0,
    "realisasi_sd": 0,
    "persen": 0.0,
    "sisa": 2720000
  },
  {
    "uraian": "000239. Topi",
    "kode_akun": null,
    "level": "item",
    "pagu": 960000,
    "realisasi_lalu": 0,
    "realisasi_ini": 0,
    "realisasi_sd": 0,
    "persen": 0.0,
    "sisa": 960000
  },
  {
    "uraian": "000240. Waterpass Dygital",
    "kode_akun": null,
    "level": "item",
    "pagu": 1710000,
    "realisasi_lalu": 0,
    "realisasi_ini": 0,
    "realisasi_sd": 0,
    "persen": 0.0,
    "sisa": 1710000
  },
  {
    "uraian": "000241. Meteran Dorong",
    "kode_akun": null,
    "level": "item",
    "pagu": 1110000,
    "realisasi_lalu": 0,
    "realisasi_ini": 0,
    "realisasi_sd": 0,
    "persen": 0.0,
    "sisa": 1110000
  },
  {
    "uraian": "000242. Meteran Laser",
    "kode_akun": null,
    "level": "item",
    "pagu": 1560000,
    "realisasi_lalu": 0,
    "realisasi_ini": 0,
    "realisasi_sd": 0,
    "persen": 0.0,
    "sisa": 1560000
  },
  {
    "uraian": "000243. Sigmat Digital",
    "kode_akun": null,
    "level": "item",
    "pagu": 560000,
    "realisasi_lalu": 0,
    "realisasi_ini": 0,
    "realisasi_sd": 0,
    "persen": 0.0,
    "sisa": 560000
  },
  {
    "uraian": "000244. Coating thickness tester",
    "kode_akun": null,
    "level": "item",
    "pagu": 3500000,
    "realisasi_lalu": 0,
    "realisasi_ini": 0,
    "realisasi_sd": 0,
    "persen": 0.0,
    "sisa": 3500000
  },
  {
    "uraian": "000245. Meteran Gulung Fiberglass",
    "kode_akun": null,
    "level": "item",
    "pagu": 840000,
    "realisasi_lalu": 0,
    "realisasi_ini": 0,
    "realisasi_sd": 0,
    "persen": 0.0,
    "sisa": 840000
  },
  {
    "uraian": "522141.0 Belanja Sewa",
    "kode_akun": "522141",
    "level": "akun",
    "pagu": 150000000,
    "realisasi_lalu": 150000000,
    "realisasi_ini": 0,
    "realisasi_sd": 150000000,
    "persen": 100.0,
    "sisa": 0
  },
  {
    "uraian": "000076. Sewa Kantor Satker P2JN",
    "kode_akun": null,
    "level": "item",
    "pagu": 150000000,
    "realisasi_lalu": 150000000,
    "realisasi_ini": 0,
    "realisasi_sd": 150000000,
    "persen": 100.0,
    "sisa": 0
  },
  {
    "uraian": "CBR.002 Layanan Perencanaan dan Pengawasan Teknik",
    "kode_akun": null,
    "level": "kegiatan",
    "pagu": 10372876000,
    "realisasi_lalu": 3138231383,
    "realisasi_ini": 677250839,
    "realisasi_sd": 3815482222,
    "persen": 36.78,
    "sisa": 6557393778
  },
  {
    "uraian": "307.0 Perencanaan Teknik (ded)",
    "kode_akun": null,
    "level": "item",
    "pagu": 5119614000,
    "realisasi_lalu": 1250468952,
    "realisasi_ini": 282997874,
    "realisasi_sd": 1533466826,
    "persen": 29.95,
    "sisa": 3586147174
  },
  {
    "uraian": "307.AH Core Team Perencanaan Bangka Belitung",
    "kode_akun": null,
    "level": "komponen",
    "pagu": 2869614000,
    "realisasi_lalu": 805199752,
    "realisasi_ini": 282997874,
    "realisasi_sd": 1088197626,
    "persen": 37.92,
    "sisa": 1781416374
  },
  {
    "uraian": "522131.0 Belanja Jasa Konsultan",
    "kode_akun": "522131",
    "level": "akun",
    "pagu": 2869614000,
    "realisasi_lalu": 805199752,
    "realisasi_ini": 282997874,
    "realisasi_sd": 1088197626,
    "persen": 37.92,
    "sisa": 1781416374
  },
  {
    "uraian": "000002. Core Team Perencanaan Bangka Belitung",
    "kode_akun": null,
    "level": "item",
    "pagu": 2869614000,
    "realisasi_lalu": 805199752,
    "realisasi_ini": 282997874,
    "realisasi_sd": 1088197626,
    "persen": 37.92,
    "sisa": 1781416374
  },
  {
    "uraian": "307.AI Perencanaan Teknis Preservasi Jalan dan Jembatan Provinsi Bangka Belitung",
    "kode_akun": null,
    "level": "komponen",
    "pagu": 2250000000,
    "realisasi_lalu": 445269200,
    "realisasi_ini": 0,
    "realisasi_sd": 445269200,
    "persen": 19.79,
    "sisa": 1804730800
  },
  {
    "uraian": "534141.0 Belanja Penambahan Nilai Jalan dan Jembatan",
    "kode_akun": "534141",
    "level": "akun",
    "pagu": 2250000000,
    "realisasi_lalu": 445269200,
    "realisasi_ini": 0,
    "realisasi_sd": 445269200,
    "persen": 19.79,
    "sisa": 1804730800
  },
  {
    "uraian": "000004. Perencanaan Teknis Preservasi Jalan dan Jembatan Provinsi Bangka Belitung",
    "kode_akun": null,
    "level": "item",
    "pagu": 2250000000,
    "realisasi_lalu": 445269200,
    "realisasi_ini": 0,
    "realisasi_sd": 445269200,
    "persen": 19.79,
    "sisa": 1804730800
  },
  {
    "uraian": "309.0 Pengawasan Teknik",
    "kode_akun": null,
    "level": "item",
    "pagu": 5253262000,
    "realisasi_lalu": 1887762431,
    "realisasi_ini": 394252965,
    "realisasi_sd": 2282015396,
    "persen": 43.44,
    "sisa": 2971246604
  },
  {
    "uraian": "309.AJ Pengawasan Teknis Preservasi Jalan dan Jembatan di Pulau Bangka Belitung",
    "kode_akun": null,
    "level": "komponen",
    "pagu": 2289018000,
    "realisasi_lalu": 716439732,
    "realisasi_ini": 280778141,
    "realisasi_sd": 997217873,
    "persen": 43.57,
    "sisa": 1291800127
  },
  {
    "uraian": "534141.0 Belanja Penambahan Nilai Jalan dan Jembatan",
    "kode_akun": "534141",
    "level": "akun",
    "pagu": 2289018000,
    "realisasi_lalu": 716439732,
    "realisasi_ini": 280778141,
    "realisasi_sd": 997217873,
    "persen": 43.57,
    "sisa": 1291800127
  },
  {
    "uraian": "000006. Pengawasan Teknis Preservasi Jalan dan Jembatan di Pulau Bangka Belitung",
    "kode_akun": null,
    "level": "item",
    "pagu": 2289018000,
    "realisasi_lalu": 716439732,
    "realisasi_ini": 280778141,
    "realisasi_sd": 997217873,
    "persen": 43.57,
    "sisa": 1291800127
  },
  {
    "uraian": "309.AK Pengawasan Teknis Penggantian Jembatan Pilang",
    "kode_akun": null,
    "level": "komponen",
    "pagu": 1741932000,
    "realisasi_lalu": 669984708,
    "realisasi_ini": 113474824,
    "realisasi_sd": 783459532,
    "persen": 44.98,
    "sisa": 958472468
  },
  {
    "uraian": "534141.0 Belanja Penambahan Nilai Jalan dan Jembatan",
    "kode_akun": "534141",
    "level": "akun",
    "pagu": 1741932000,
    "realisasi_lalu": 669984708,
    "realisasi_ini": 113474824,
    "realisasi_sd": 783459532,
    "persen": 44.98,
    "sisa": 958472468
  },
  {
    "uraian": "000008. Pengawasan Teknis Penggantian Jembatan Pilang",
    "kode_akun": null,
    "level": "item",
    "pagu": 1741932000,
    "realisasi_lalu": 669984708,
    "realisasi_ini": 113474824,
    "realisasi_sd": 783459532,
    "persen": 44.98,
    "sisa": 958472468
  },
  {
    "uraian": "309.AL Pengawasan Teknis Penggantian Jembatan Air Liring",
    "kode_akun": null,
    "level": "komponen",
    "pagu": 1222312000,
    "realisasi_lalu": 501337991,
    "realisasi_ini": 0,
    "realisasi_sd": 501337991,
    "persen": 41.02,
    "sisa": 720974009
  },
  {
    "uraian": "534141.0 Belanja Penambahan Nilai Jalan dan Jembatan",
    "kode_akun": "534141",
    "level": "akun",
    "pagu": 1222312000,
    "realisasi_lalu": 501337991,
    "realisasi_ini": 0,
    "realisasi_sd": 501337991,
    "persen": 41.02,
    "sisa": 720974009
  },
  {
    "uraian": "000163. Pengawasan Teknis Penggantian Jembatan Air Liring",
    "kode_akun": null,
    "level": "item",
    "pagu": 1222312000,
    "realisasi_lalu": 501337991,
    "realisasi_ini": 0,
    "realisasi_sd": 501337991,
    "persen": 41.02,
    "sisa": 720974009
  },
  {
    "uraian": "WA Program Dukungan Manajemen",
    "kode_akun": null,
    "level": "program",
    "pagu": 621070000,
    "realisasi_lalu": 213114283,
    "realisasi_ini": 16385283,
    "realisasi_sd": 229499566,
    "persen": 36.95,
    "sisa": 391570434
  },
  {
    "uraian": "WA.7756 Dukungan Manajemen Ditjen Bina Marga",
    "kode_akun": null,
    "level": "program",
    "pagu": 621070000,
    "realisasi_lalu": 213114283,
    "realisasi_ini": 16385283,
    "realisasi_sd": 229499566,
    "persen": 36.95,
    "sisa": 391570434
  },
  {
    "uraian": "EBA Layanan Dukungan Manajemen Internal",
    "kode_akun": null,
    "level": "kegiatan",
    "pagu": 564682000,
    "realisasi_lalu": 156726283,
    "realisasi_ini": 16385283,
    "realisasi_sd": 173111566,
    "persen": 30.66,
    "sisa": 391570434
  },
  {
    "uraian": "EBA.994 Layanan Perkantoran",
    "kode_akun": null,
    "level": "kegiatan",
    "pagu": 564682000,
    "realisasi_lalu": 156726283,
    "realisasi_ini": 16385283,
    "realisasi_sd": 173111566,
    "persen": 30.66,
    "sisa": 391570434
  },
  {
    "uraian": "2.0 Operasional dan Pemeliharaan Kantor",
    "kode_akun": null,
    "level": "item",
    "pagu": 564682000,
    "realisasi_lalu": 156726283,
    "realisasi_ini": 16385283,
    "realisasi_sd": 173111566,
    "persen": 30.66,
    "sisa": 391570434
  },
  {
    "uraian": "002.BE Penyelenggaraan Operasional dan Pemeliharaan Perkantoran",
    "kode_akun": null,
    "level": "komponen",
    "pagu": 473675000,
    "realisasi_lalu": 156726283,
    "realisasi_ini": 16385283,
    "realisasi_sd": 173111566,
    "persen": 36.55,
    "sisa": 300563434
  },
  {
    "uraian": "521111.0 Belanja Keperluan Perkantoran",
    "kode_akun": "521111",
    "level": "akun",
    "pagu": 134795000,
    "realisasi_lalu": 41772476,
    "realisasi_ini": 7485283,
    "realisasi_sd": 49257759,
    "persen": 36.54,
    "sisa": 85537241
  },
  {
    "uraian": "000082. keperluan Sehari-hari Perkantoran kurang 40 Pegawai (Bangka Belitung)",
    "kode_akun": null,
    "level": "item",
    "pagu": 56620000,
    "realisasi_lalu": 26163531,
    "realisasi_ini": 3581000,
    "realisasi_sd": 29744531,
    "persen": 52.53,
    "sisa": 26875469
  },
  {
    "uraian": "000083. Makan Rapat Biasa BANGKA  BELITUNG",
    "kode_akun": null,
    "level": "item",
    "pagu": 5625000,
    "realisasi_lalu": 0,
    "realisasi_ini": 0,
    "realisasi_sd": 0,
    "persen": 0.0,
    "sisa": 5625000
  },
  {
    "uraian": "000084. Snack Rapat Biasa BANGKA  BELITUNG",
    "kode_akun": null,
    "level": "item",
    "pagu": 4150000,
    "realisasi_lalu": 0,
    "realisasi_ini": 0,
    "realisasi_sd": 0,
    "persen": 0.0,
    "sisa": 4150000
  },
  {
    "uraian": "000085. Langganan Internet 350 Mbps",
    "kode_akun": null,
    "level": "item",
    "pagu": 68400000,
    "realisasi_lalu": 15608945,
    "realisasi_ini": 3904283,
    "realisasi_sd": 19513228,
    "persen": 28.53,
    "sisa": 48886772
  },
  {
    "uraian": "521115.0 Belanja Honor Operasional Satuan Kerja",
    "kode_akun": "521115",
    "level": "akun",
    "pagu": 115440000,
    "realisasi_lalu": 26700000,
    "realisasi_ini": 8900000,
    "realisasi_sd": 35600000,
    "persen": 30.84,
    "sisa": 79840000
  },
  {
    "uraian": "000087. Honorarium Pejabat Pembuat Komitmen (Nilai pagu dana di atas Rp1 miliar s.d. Rp10 miliar)",
    "kode_akun": null,
    "level": "item",
    "pagu": 13800000,
    "realisasi_lalu": 3450000,
    "realisasi_ini": 1150000,
    "realisasi_sd": 4600000,
    "persen": 33.33,
    "sisa": 9200000
  },
  {
    "uraian": "000088. Honorarium Staf  Pengelola (Nilai pagu dana di atas Rp1 miliar s.d. Rp10 miliar)",
    "kode_akun": null,
    "level": "item",
    "pagu": 7200000,
    "realisasi_lalu": 1800000,
    "realisasi_ini": 600000,
    "realisasi_sd": 2400000,
    "persen": 33.33,
    "sisa": 4800000
  },
  {
    "uraian": "000090. Honorarium Pejabat Kuasa Pengguna Anggaran (Nilai pagu dana di atas Rp1 miliar s.d. Rp10 miliar)",
    "kode_akun": null,
    "level": "item",
    "pagu": 13800000,
    "realisasi_lalu": 3450000,
    "realisasi_ini": 1150000,
    "realisasi_sd": 4600000,
    "persen": 33.33,
    "sisa": 9200000
  },
  {
    "uraian": "000091. Honorarium Staf  Pengelola (Nilai pagu dana di atas Rp1 miliar s.d. Rp10 miliar)",
    "kode_akun": null,
    "level": "item",
    "pagu": 7200000,
    "realisasi_lalu": 1800000,
    "realisasi_ini": 600000,
    "realisasi_sd": 2400000,
    "persen": 33.33,
    "sisa": 4800000
  },
  {
    "uraian": "000092. Honorarium Pejabat Kuasa Pengguna Anggaran (Nilai pagu dana di atas Rp10 miliar s.d. Rp100 miliar)",
    "kode_akun": null,
    "level": "item",
    "pagu": 21600000,
    "realisasi_lalu": 3540000,
    "realisasi_ini": 1180000,
    "realisasi_sd": 4720000,
    "persen": 21.85,
    "sisa": 16880000
  },
  {
    "uraian": "000093. Honorarium Pejabat  Penguji Tagihan   Penandatangan  Spm (Nilai pagu dana di atas Rp10 miliar s.d. Rp100 miliar)",
    "kode_akun": null,
    "level": "item",
    "pagu": 9000000,
    "realisasi_lalu": 2250000,
    "realisasi_ini": 750000,
    "realisasi_sd": 3000000,
    "persen": 33.33,
    "sisa": 6000000
  },
  {
    "uraian": "000094. Honorarium Staf  Pengelola (Nilai pagu dana di atas Rp10 miliar s.d. Rp100 miliar)",
    "kode_akun": null,
    "level": "item",
    "pagu": 17640000,
    "realisasi_lalu": 4410000,
    "realisasi_ini": 1470000,
    "realisasi_sd": 5880000,
    "persen": 33.33,
    "sisa": 11760000
  },
  {
    "uraian": "000095. Honorarium Bendahara  Pengeluaran (Nilai pagu dana di atas Rp10 miliar s.d. Rp100 miliar)",
    "kode_akun": null,
    "level": "item",
    "pagu": 7920000,
    "realisasi_lalu": 1980000,
    "realisasi_ini": 660000,
    "realisasi_sd": 2640000,
    "persen": 33.33,
    "sisa": 5280000
  },
  {
    "uraian": "000096. Honorarium Pengurus/Penyimpan Bmn Tingkat Kuasa Pengguna Barang",
    "kode_akun": null,
    "level": "item",
    "pagu": 4320000,
    "realisasi_lalu": 1080000,
    "realisasi_ini": 360000,
    "realisasi_sd": 1440000,
    "persen": 33.33,
    "sisa": 2880000
  },
  {
    "uraian": "000097. Honorarium Penanggung Jawab (UAKPA/Barang)",
    "kode_akun": null,
    "level": "item",
    "pagu": 4800000,
    "realisasi_lalu": 900000,
    "realisasi_ini": 300000,
    "realisasi_sd": 1200000,
    "persen": 25.0,
    "sisa": 3600000
  },
  {
    "uraian": "000098. Honorarium Pejabat Pengadaan Barang/Jasa",
    "kode_akun": null,
    "level": "item",
    "pagu": 8160000,
    "realisasi_lalu": 2040000,
    "realisasi_ini": 680000,
    "realisasi_sd": 2720000,
    "persen": 33.33,
    "sisa": 5440000
  },
  {
    "uraian": "521811.0 Belanja Barang Persediaan Barang Konsumsi",
    "kode_akun": "521811",
    "level": "akun",
    "pagu": 50700000,
    "realisasi_lalu": 41472600,
    "realisasi_ini": 0,
    "realisasi_sd": 41472600,
    "persen": 81.8,
    "sisa": 9227400
  },
  {
    "uraian": "000101. Alat Tulis Kantor (ATK)",
    "kode_akun": null,
    "level": "item",
    "pagu": 25200000,
    "realisasi_lalu": 23141000,
    "realisasi_ini": 0,
    "realisasi_sd": 23141000,
    "persen": 91.83,
    "sisa": 2059000
  },
  {
    "uraian": "000102. Peralatan Komputer",
    "kode_akun": null,
    "level": "item",
    "pagu": 25500000,
    "realisasi_lalu": 18331600,
    "realisasi_ini": 0,
    "realisasi_sd": 18331600,
    "persen": 71.89,
    "sisa": 7168400
  },
  {
    "uraian": "522111.0 Belanja Langganan Listrik",
    "kode_akun": "522111",
    "level": "akun",
    "pagu": 84000000,
    "realisasi_lalu": 25421500,
    "realisasi_ini": 0,
    "realisasi_sd": 25421500,
    "persen": 30.26,
    "sisa": 58578500
  },
  {
    "uraian": "000104. Langganan Listrik",
    "kode_akun": null,
    "level": "item",
    "pagu": 84000000,
    "realisasi_lalu": 25421500,
    "realisasi_ini": 0,
    "realisasi_sd": 25421500,
    "persen": 30.26,
    "sisa": 58578500
  },
  {
    "uraian": "523121.0 Belanja Pemeliharaan Peralatan dan Mesin",
    "kode_akun": "523121",
    "level": "akun",
    "pagu": 88740000,
    "realisasi_lalu": 21359707,
    "realisasi_ini": 0,
    "realisasi_sd": 21359707,
    "persen": 24.07,
    "sisa": 67380293
  },
  {
    "uraian": "000106. Biaya Pemeliharaan dan Operasional Kendaraan Roda 4 (Bangka  Belitung)",
    "kode_akun": null,
    "level": "item",
    "pagu": 34838000,
    "realisasi_lalu": 14269707,
    "realisasi_ini": 0,
    "realisasi_sd": 14269707,
    "persen": 40.96,
    "sisa": 20568293
  },
  {
    "uraian": "000107. Biaya Pemeliharaan dan Operasional Kendaraan Roda 2 (Bangka  Belitung)",
    "kode_akun": null,
    "level": "item",
    "pagu": 18734000,
    "realisasi_lalu": 0,
    "realisasi_ini": 0,
    "realisasi_sd": 0,
    "persen": 0.0,
    "sisa": 18734000
  },
  {
    "uraian": "000108. Pemeliharaan Genset lebih kecil dari 50 KVA",
    "kode_akun": null,
    "level": "item",
    "pagu": 6830000,
    "realisasi_lalu": 0,
    "realisasi_ini": 0,
    "realisasi_sd": 0,
    "persen": 0.0,
    "sisa": 6830000
  },
  {
    "uraian": "000109. Pemeliharaan AC Split",
    "kode_akun": null,
    "level": "item",
    "pagu": 2897000,
    "realisasi_lalu": 2850000,
    "realisasi_ini": 0,
    "realisasi_sd": 2850000,
    "persen": 98.38,
    "sisa": 47000
  },
  {
    "uraian": "000110. Pemeliharaan Personal Computer/Notebook",
    "kode_akun": null,
    "level": "item",
    "pagu": 16644000,
    "realisasi_lalu": 4240000,
    "realisasi_ini": 0,
    "realisasi_sd": 4240000,
    "persen": 25.47,
    "sisa": 12404000
  },
  {
    "uraian": "000111. Pemeliharaan Printer/Scanner",
    "kode_akun": null,
    "level": "item",
    "pagu": 8797000,
    "realisasi_lalu": 0,
    "realisasi_ini": 0,
    "realisasi_sd": 0,
    "persen": 0.0,
    "sisa": 8797000
  },
  {
    "uraian": "002.BF Pemeliharaan Gedung",
    "kode_akun": null,
    "level": "komponen",
    "pagu": 52903000,
    "realisasi_lalu": 0,
    "realisasi_ini": 0,
    "realisasi_sd": 0,
    "persen": 0.0,
    "sisa": 52903000
  },
  {
    "uraian": "523111.0 Belanja Pemeliharaan Gedung dan Bangunan",
    "kode_akun": "523111",
    "level": "akun",
    "pagu": 52903000,
    "realisasi_lalu": 0,
    "realisasi_ini": 0,
    "realisasi_sd": 0,
    "persen": 0.0,
    "sisa": 52903000
  },
  {
    "uraian": "000113. Pemeliharaan Gedung/Bangunan (Bangka  Belitung)",
    "kode_akun": null,
    "level": "item",
    "pagu": 52903000,
    "realisasi_lalu": 0,
    "realisasi_ini": 0,
    "realisasi_sd": 0,
    "persen": 0.0,
    "sisa": 52903000
  },
  {
    "uraian": "002.BG Belanja Barang Operasional Lainnya",
    "kode_akun": null,
    "level": "komponen",
    "pagu": 38104000,
    "realisasi_lalu": 0,
    "realisasi_ini": 0,
    "realisasi_sd": 0,
    "persen": 0.0,
    "sisa": 38104000
  },
  {
    "uraian": "521119.0 Belanja Barang Operasional Lainnya",
    "kode_akun": "521119",
    "level": "akun",
    "pagu": 38104000,
    "realisasi_lalu": 0,
    "realisasi_ini": 0,
    "realisasi_sd": 0,
    "persen": 0.0,
    "sisa": 38104000
  },
  {
    "uraian": "000246. Rompi Lapangan",
    "kode_akun": null,
    "level": "item",
    "pagu": 5600000,
    "realisasi_lalu": 0,
    "realisasi_ini": 0,
    "realisasi_sd": 0,
    "persen": 0.0,
    "sisa": 5600000
  },
  {
    "uraian": "000247. Helm safety",
    "kode_akun": null,
    "level": "item",
    "pagu": 1600000,
    "realisasi_lalu": 0,
    "realisasi_ini": 0,
    "realisasi_sd": 0,
    "persen": 0.0,
    "sisa": 1600000
  },
  {
    "uraian": "000248. Topi",
    "kode_akun": null,
    "level": "item",
    "pagu": 1600000,
    "realisasi_lalu": 0,
    "realisasi_ini": 0,
    "realisasi_sd": 0,
    "persen": 0.0,
    "sisa": 1600000
  },
  {
    "uraian": "000249. Sepatu Safety",
    "kode_akun": null,
    "level": "item",
    "pagu": 10400000,
    "realisasi_lalu": 0,
    "realisasi_ini": 0,
    "realisasi_sd": 0,
    "persen": 0.0,
    "sisa": 10400000
  },
  {
    "uraian": "000250. Pakaian Training",
    "kode_akun": null,
    "level": "item",
    "pagu": 6400000,
    "realisasi_lalu": 0,
    "realisasi_ini": 0,
    "realisasi_sd": 0,
    "persen": 0.0,
    "sisa": 6400000
  },
  {
    "uraian": "000251. Rain Coat",
    "kode_akun": null,
    "level": "item",
    "pagu": 4000000,
    "realisasi_lalu": 0,
    "realisasi_ini": 0,
    "realisasi_sd": 0,
    "persen": 0.0,
    "sisa": 4000000
  },
  {
    "uraian": "000252. Alat Pemadam Api Ringan (APAR) 3 Kg",
    "kode_akun": null,
    "level": "item",
    "pagu": 1600000,
    "realisasi_lalu": 0,
    "realisasi_ini": 0,
    "realisasi_sd": 0,
    "persen": 0.0,
    "sisa": 1600000
  },
  {
    "uraian": "000253. Safety Traffic Cone",
    "kode_akun": null,
    "level": "item",
    "pagu": 450000,
    "realisasi_lalu": 0,
    "realisasi_ini": 0,
    "realisasi_sd": 0,
    "persen": 0.0,
    "sisa": 450000
  },
  {
    "uraian": "000254. Meteran 7,5 m",
    "kode_akun": null,
    "level": "item",
    "pagu": 720000,
    "realisasi_lalu": 0,
    "realisasi_ini": 0,
    "realisasi_sd": 0,
    "persen": 0.0,
    "sisa": 720000
  },
  {
    "uraian": "000255. Meteran Dorong",
    "kode_akun": null,
    "level": "item",
    "pagu": 900000,
    "realisasi_lalu": 0,
    "realisasi_ini": 0,
    "realisasi_sd": 0,
    "persen": 0.0,
    "sisa": 900000
  },
  {
    "uraian": "000256. Crack Scale Card",
    "kode_akun": null,
    "level": "item",
    "pagu": 960000,
    "realisasi_lalu": 0,
    "realisasi_ini": 0,
    "realisasi_sd": 0,
    "persen": 0.0,
    "sisa": 960000
  },
  {
    "uraian": "000257. Alat Ukur Jarak Laser",
    "kode_akun": null,
    "level": "item",
    "pagu": 800000,
    "realisasi_lalu": 0,
    "realisasi_ini": 0,
    "realisasi_sd": 0,
    "persen": 0.0,
    "sisa": 800000
  },
  {
    "uraian": "000258. Meteran Gulung Fiberglass 50 m",
    "kode_akun": null,
    "level": "item",
    "pagu": 400000,
    "realisasi_lalu": 0,
    "realisasi_ini": 0,
    "realisasi_sd": 0,
    "persen": 0.0,
    "sisa": 400000
  },
  {
    "uraian": "000259. Thermometer Infrared Digital",
    "kode_akun": null,
    "level": "item",
    "pagu": 1724000,
    "realisasi_lalu": 0,
    "realisasi_ini": 0,
    "realisasi_sd": 0,
    "persen": 0.0,
    "sisa": 1724000
  },
  {
    "uraian": "000260. Tangga Teleskopik",
    "kode_akun": null,
    "level": "item",
    "pagu": 950000,
    "realisasi_lalu": 0,
    "realisasi_ini": 0,
    "realisasi_sd": 0,
    "persen": 0.0,
    "sisa": 950000
  },
  {
    "uraian": "EBB Layanan Sarana dan Prasarana Internal",
    "kode_akun": null,
    "level": "kegiatan",
    "pagu": 56388000,
    "realisasi_lalu": 56388000,
    "realisasi_ini": 0,
    "realisasi_sd": 56388000,
    "persen": 100.0,
    "sisa": 0
  },
  {
    "uraian": "EBB.951 Layanan Sarana Internal",
    "kode_akun": null,
    "level": "kegiatan",
    "pagu": 56388000,
    "realisasi_lalu": 56388000,
    "realisasi_ini": 0,
    "realisasi_sd": 56388000,
    "persen": 100.0,
    "sisa": 0
  },
  {
    "uraian": "52.0 Pengadaan Perangkat Pengolah Data Dan Komunikasi",
    "kode_akun": null,
    "level": "item",
    "pagu": 56388000,
    "realisasi_lalu": 56388000,
    "realisasi_ini": 0,
    "realisasi_sd": 56388000,
    "persen": 100.0,
    "sisa": 0
  },
  {
    "uraian": "052.CA Pengadaan Perangkat Pengolah Data dan Komunikasi",
    "kode_akun": null,
    "level": "komponen",
    "pagu": 56388000,
    "realisasi_lalu": 56388000,
    "realisasi_ini": 0,
    "realisasi_sd": 56388000,
    "persen": 100.0,
    "sisa": 0
  },
  {
    "uraian": "532111.0 Belanja Modal Peralatan dan Mesin",
    "kode_akun": "532111",
    "level": "akun",
    "pagu": 56388000,
    "realisasi_lalu": 56388000,
    "realisasi_ini": 0,
    "realisasi_sd": 56388000,
    "persen": 100.0,
    "sisa": 0
  },
  {
    "uraian": "000207. Perangkat Pengolahan Data dan Komunikasi",
    "kode_akun": null,
    "level": "item",
    "pagu": 56388000,
    "realisasi_lalu": 56388000,
    "realisasi_ini": 0,
    "realisasi_sd": 56388000,
    "persen": 100.0,
    "sisa": 0
  }
]